darca_space_manager/__init__.py
darca_space_manager/__version__.py
darca_space_manager/config.py
darca_space_manager/space_executor.py
darca_space_manager/space_file_manager.py
darca_space_manager/space_manager.py
darca_space_manager-0.6.1.dist-info/LICENSE
darca_space_manager-0.6.1.dist-info/METADATA
darca_space_manager-0.6.1.dist-info/WHEEL
darca_space_manager-0.6.1.dist-info/RECORD
