Metadata-Version: 2.3
Name: darca-space-manager
Version: 0.6.1
Summary: Storage abstraction layer for managing logical spaces.
License: LICENSE
Author: Roel Kist
Author-email: roel.kist@gmail.com
Requires-Python: >=3.12,<4.0
Classifier: License :: Other/Proprietary License
Classifier: Programming Language :: Python :: 3
Classifier: Programming Language :: Python :: 3.12
Classifier: Programming Language :: Python :: 3.13
Requires-Dist: darca-exception (>=0.1.0,<0.2.0)
Requires-Dist: darca-executor (>=0.1.0,<0.2.0)
Requires-Dist: darca-file-utils (>=0.1.0,<0.2.0)
Requires-Dist: darca-log-facility (>=0.1.0,<0.2.0)
Requires-Dist: darca-yaml (>=0.2.0,<0.3.0)
